{"bookId":"1053","level":"x","title":"Many Happy Returns","subtle":"Realistic (fiction), 1,811 words, Level X (Grade 5), Lexile 900L","description":"Jess is very upset. Not only did he lose his pet bird, but he cannot master the technique of throwing a boomerang, and is having difficulty making friends with some kids at school. Many Happy Returns is a realistic fiction book about a boy who is searching for his dove while venting his frustration to an old boomerang-slinger champ. M'Gwump, Jess's Australian grandpa, teaches the young boy a life lesson through his wisdom and hobby of throwing a boomerang. This engaging book encourages students to practice analyzing the plot and identifying similes.","pageCount":18,"highFrequencyWords":"avian, boomerang, desperate, dilemma, distract, enthusiasm, knack, recreation, understatement, wonderment","reviewWords":"Use of vocabulary lessons requires a subscription to VocabularyA-Z.com.","comprehension":"Commas                : Recognize and use of commas to separate dialogue","awareness":"Similes                : Identify similies","phonics":"Promote higher-order thinking for small groups <br>or whole class","grammar":"","wordWork":"","pdfName":"raz_lx00_manyhappy"}