{"bookId":"108","level":"h","title":"Maria's Thanksgiving","subtle":"Realistic (fiction), 214 words, Level H (Grade 1), Lexile 490L, Fiction Series","description":"If you've ever looked forward to a big holiday event and had it canceled due to weather, you'll relate to this realistic fiction book. At the start of the story, Maria reminisces about past Thanksgivings. She remembers relatives gathering at her home, the foods family members brought, and the activities that everyone shared. Then a big snowstorm prevents the traditional family gathering. At first Maria and her neighbors fear that Thanksgiving is ruined. Then Maria comes up with a plan that honors the true meaning of Thanksgiving.","pageCount":15,"highFrequencyWords":"brought, come, made","reviewWords":"holiday, neighbors, pasta, stuffing, sweet potatoes, tamales, thankful, Thanksgiving, turkey","comprehension":"Sequence Events                : Sequence story events","awareness":"Blend Sounds                : Blend segmented sounds into words","phonics":"Vowel Digraphs                : Identify and read words that contain long \/e\/ vowel digraphs","grammar":"Possessives                : Understand and read the possessive form of words","wordWork":"Compound Words                : Locate and read compound words","pdfName":"raz_lh12_mariathanks"}