{"bookId":"1098","level":"f","title":"Does It Sink or Float?","subtle":"Informational (nonfiction), 137 words, Level F (Grade 1), Lexile 180L","description":"In Does It Sink or Float? students have the opportunity to use what they know about familiar objects to determine whether each will sink or float in water. Interesting photographs are included to enhance student understanding of the concepts sink and float. Repetitive phrases and high-frequency words support early readers.","pageCount":13,"highFrequencyWords":"in, some, will","reviewWords":"float, golf ball, marble, penny, sink, watermelon","comprehension":"Author's Purpose                : Identify the author's purpose","awareness":"Initial Blends                : Discriminate initial consonant blend \/fl\/ sound","phonics":"Consonant Blends                : Identify initial consonant blend <em>fl<\/em>","grammar":"Punctuation                : Recognize, identify, and use question marks","wordWork":"High-Frequency Words                : Understand, use, and write the high-frequency word <em>will<\/em>","pdfName":"raz_lf22_doesitsink"}