{"bookId":"1134","level":"c","title":"What Do I Wear?","subtle":"Informational (nonfiction), 39 words, Level C (Grade K), Lexile 40L","description":"In What Do I Wear?, a girl is getting dressed. She tells where pieces of clothing and other items are worn on the body. Patterned text, the high-frequency word a, and supportive pictures make this book perfect for emerging readers.","pageCount":11,"highFrequencyWords":"a","reviewWords":"chest, heart, smile, waist, wears, wrist","comprehension":"Classify Information                : Classify information","awareness":"Initial Consonants                : Discriminate initial \/w\/ sound","phonics":"Consonants                : Identify initial consonant <em>Ww<\/em>","grammar":"Nouns                : Identify nouns as naming words","wordWork":"High-Frequency Words                : Identify and write the high-frequency word <em>a<\/em>","pdfName":"raz_lc24_whatdoiwear"}