{"id":"1160","level":"t","title":"Morty and the Mousetown Gazette","subtle":"Fantasy (fiction), 1,834 words, Level T (Grade 3), Lexile 860L, Fiction Series","description":"Morty Mouse couldn't believe he finally had a chance to become a newspaper carrier. His friend Ben asked him to cover his route for three days, and if Morty did a good job, he just might get his own job. Will Morty see his dream of being a newspaper carrier become a reality? Students will learn about the importance of dependability and honesty as Morty discovers if he is ready for the responsibility of having a job. Illustrations support the text.","count":21,"from":1,"meta":["convince, deadline, delivery, diligence, familiar, funeral, mistake, refund, responsibility, route, shrill, tip","Use the reading strategy of making, revising, and confirming predictions to understand the text","Cause and Effect : Understand and identify cause-and-effect relationships","Compound Sentences : Identify compound sentences used in text","Homophones : Identify and use homophones","Promote higher-order thinking for small groups <br>or whole class"],"pdfs":["pdfsite\/morty\/raz_mm08_mousegazette_wksh.pdf","pdfsite\/worksheets\/site_and_dist\/morty\/raz_mm08_mousegazette_wksh_rs.pdf","pdfsite\/worksheets\/site_and_dist\/morty\/raz_mm08_mousegazette_wksh_rc.pdf","pdfsite\/worksheets\/site_and_dist\/morty\/raz_mm08_mousegazette_wksh_gm.pdf","pdfsite\/worksheets\/site_and_dist\/morty\/raz_mm08_mousegazette_wksh_ww.pdf","pdfsite\/morty\/raz_mm08_mousegazette_dc.pdf","pdfsite\/comp_quiz\/t\/raz_mmcqlt07_mousegazette.pdf"],"mis":{"clr":"pdfsite\/morty\/raz_mm08_mousegazette_clr_ds.pdf","lblp":"pdfsite\/lesson_plans\/site_and_dist\/morty\/raz_mm08_mousegazette_lp.pdf"}}