{"id":"1407","level":"p","title":"World Cup Soccer","subtle":"Informational (nonfiction), 662 words, Level P (Grade 2), Lexile 970L","description":"World Cup Soccer introduces the reader to the world of professional soccer, the best- loved sport in the world! Learn fascinating facts about the game's history, best teams and players, and why it is called \u201cthe people's game.\u201d","count":17,"from":1,"meta":["accidentally, championship, goalkeeper, host, legends, lively, tournament, uniform, upsets","Use the reading strategy of connecting to prior knowledge to understand nonfiction text","Main Idea and Details : Identify main idea and details in the text","R-Controlled Vowels : Identify <em>r<\/em>-controlled <em>er<\/em> vowel","Quotation Marks : Understand alternative uses of quotation marks","Suffixes : Understand the use of <em>-ing<\/em> suffix","Promote higher-order thinking for small groups <br>or whole class"],"pdfs":["pdfsite\/worksheets\/p\/raz_lp36_worldcupsoccer_wksh.pdf","pdfsite\/worksheets\/p\/raz_lp36_worldcupsoccer_wksh_rs.pdf","pdfsite\/worksheets\/p\/raz_lp36_worldcupsoccer_wksh_rc.pdf","pdfsite\/worksheets\/p\/raz_lp36_worldcupsoccer_wksh_ww.pdf","pdfsite\/discussion\/p\/raz_dclp36_worldcupsoccer.pdf","pdfsite\/comp_quiz\/p\/raz_cqlp36_worldcupsoccer.pdf"],"mis":{"clr":"pdfsite\/levels\/p_ds\/raz_lp36_worldcupsoccer_clr_ds.pdf","lblp":"pdfsite\/lesson_plans\/p\/raz_lp36_worldcupsoccer_lp.pdf"}}