{"bookId":"1526","level":"w","title":"To Drill or Not to Drill?","subtle":"Pro\/Con (nonfiction), 2,161 words, Level W (Grade 4), Lexile 990L","description":"To Drill or Not to Drill? gives readers information on both sides of a heated debate: whether or not to drill for oil in Alaska's Arctic National Wildlife Refuge (ANWR). The book includes a history of American oil along with reasons to drill in ANWR, reasons not to drill, and the science and law behind it all. Photographs, maps, and graphs support the text.","pageCount":25,"highFrequencyWords":"crisis, endangered, estimate, fuel efficient, geologist, imports, independence, migration, preserve, sprawl, threatened, tundra","reviewWords":"Use of vocabulary lessons requires a subscription to VocabularyA-Z.com.","comprehension":"Complex Sentences                : Identify parts of a complex sentence","awareness":"Roots                : Identify root words","phonics":"Promote higher-order thinking for small groups <br>or whole class","grammar":"","wordWork":"","pdfName":"raz_lw29_todrillornottodrill"}