{"bookId":"1695","level":"f","title":"Two for Me, One for You","subtle":"Realistic (fiction), 159 words, Level F (Grade 1), Lexile 300L","description":"What should Mom do in the story Two for Me, One for You? Justin wants all the toys for himself, but Mom says he must share with Eric. What happens when Justin splits the toys into two piles? Students can sequence events as well as connect to prior knowledge. Supportive illustrations and high-frequency words support emergent readers.","pageCount":13,"highFrequencyWords":"he, into, puts","reviewWords":"bigger, equal, mad, piles, share, split","comprehension":"Sequence Events                : Sequence events","awareness":"Segment Onset and Rime                : Segment onset and rime","phonics":"Short Vowels                : Identify short vowel <em>a<\/em>","grammar":"Proper Nouns                : Recognize and use proper nouns: names of people","wordWork":"Concept Words                : Understand, use, and write number words","pdfName":"raz_lf38_twomeoneyou"}