{"bookId":"1723","level":"h","title":"Blackbeard the Pirate","subtle":"Biography (nonfiction), 236 words, Level H (Grade 1), Lexile 520L            \n                        \n\t\tMultilevel Book also available in levels                     K and N","description":"Blackbeard the Pirate tells the true story of the famous pirate who terrorized the seas for years. Born in the late 1600s, he learned to sail at an early age. Once he began robbing ships, Blackbeard became one of the most feared pirates on the sea until he was killed in battle. Blackbeard's true story is the inspiration behind many of the colorful pirates in today's books and movies. Photographs, illustrations, and maps support the text. Book and lesson also available at Levels K and N.","pageCount":17,"highFrequencyWords":"was, very","reviewWords":"pirate, real, rob, sailed, skeleton, treasure","comprehension":"Author's Purpose                : Identify the author's purpose","awareness":"Segment Syllables                : Segment syllables","phonics":"Vowel Digraphs                : Identify vowel digraph<em> ea<\/em>","grammar":"Past-Tense Verbs                : Identify and understand past-tense verbs","wordWork":"Suffixes                : Recognize the suffix <em>-ed<\/em> and understand the formation of past-tense verbs","pdfName":"raz_lh34_blackbeardpirate"}