{"id":"1827","level":"aa","title":"My School Bus","subtle":"Concept (nonfiction), 16 words, Level aa (Grade K), Lexile BR70L","description":"This simple book combines bold, colorful illustrations and two-word sentences to deliver information about a topic familiar to many students: riding a school bus. The text and illustrations cover the steps involved in riding a school bus. Students have the opportunity to learn about main ideas and details as well as the use of periods in a sentence.","count":11,"from":1,"meta":["the","bench, bus, door, school, seat, steps, walk, window","Connect to prior knowledge to understand text","Main Idea and Details : Identify main idea and details","Initial Consonants : Discriminate initial consonant \/w\/ sound","Consonants : Identify initial consonant <em>Ww<\/em>","Periods : Recognize and use periods","Alphabetical Order : Arrange words in alphabetical order"],"pdfs":["pdfsite\/1827\/raz_laa51_myschoolbus_wksh.pdf","pdfsite\/1827\/raz_laa51_myschoolbus_wksh_rc.pdf","pdfsite\/1827\/raz_laa51_myschoolbus_wksh_ph.pdf","pdfsite\/1827\/raz_laa51_myschoolbus_wksh_gm.pdf"],"mis":{"clr":"pdfs\/levels\/aa\/raz_laa51_myschoolbus_clr_ds.pdf","lblp":"pdfsite\/1827\/raz_laa51_myschoolbus_lp.pdf"}}