{"id":"1898","level":"m","title":"Parrots","subtle":"Informational (nonfiction), 505 words, Level M (Grade 2), Lexile 670L","description":"Parrots are beautiful and intelligent animals that thrive in tropical and subtropical habitats throughout the world. Find out how parrots are different from other birds and learn what they all have in common. Students will enjoy reading about the many kinds of parrots and their special characteristics.","count":17,"from":1,"meta":["bills, communicate, crest, mimic, nectar, rainforests, reason, subtropical, tropical","Ask and answer questions to understand text","Compare and Contrast : Compare and contrast","Consonant Digraphs : Identify consonant <i>th<\/i> digraph","Adjectives : Recognize and use adjectives","Suffixes : Identify and understand the use of suffix <i>-ing<\/i>","Promote higher-order thinking for small groups <br>or whole class"],"pdfs":["pdfsite\/nonbooks\/common_core_supplement\/parrots_ccss_lp.pdf","pdfsite\/1898\/raz_lm27_parrots_wksh.pdf","pdfsite\/1898\/raz_lm27_parrots_wksh_rs.pdf","pdfsite\/1898\/raz_lm27_parrots_wksh_rc.pdf","pdfsite\/1898\/raz_lm27_parrots_wksh_gm.pdf","pdfsite\/discussion\/m\/raz_dclm27_parrots.pdf","pdfsite\/comp_quiz\/m\/raz_cqlm27_parrots.pdf"],"mis":{"clr":"pdfs\/levels\/m\/raz_lm27_parrots_clr_ds.pdf","lblp":"pdfsite\/1898\/raz_lm27_parrots_lp.pdf"}}