{"bookId":"1927","level":"s","title":"Voyagers in Space","subtle":"Informational (nonfiction), 952 words, Level S (Grade 3), Lexile 960L            \n                        \n\t\tMultilevel Book also available in levels                     M and P\t\t                 \n\t\tMultilevel Book also available in levels                     M and P","description":"Two unmanned Voyager spacecraft were launched in 1977 with a mission of studying the large outer planets of our solar system. Voyagers in Space describes their journeys, the information the Voyagers learned about the giant planets, and their current task of exploring deep space. Photographs, diagrams, and time lines support the text. Build on students' intrinsic interest in space exploration to teach about distinguishing between fact and opinion and using past-tense verbs. Book and lesson are also available for Levels M and P.","pageCount":17,"highFrequencyWords":"expore, gravity, instruments, interstellar, mission, orbits, plasma, probes, solar system","reviewWords":"Use of vocabulary lessons requires a subscription to VocabularyA-Z.com.","comprehension":"Past-Tense Verbs                : Identify and use past-tense verbs","awareness":"Compound Words                : Recognize and use open compound words","phonics":"Promote higher-order thinking for small groups <br>or whole class","grammar":"","wordWork":"","pdfName":"raz_ls37_voyagersinspace"}