{"id":"1930","level":"a","title":"I Love Flowers","subtle":"Concept (nonfiction), 24 words, Level A (Grade K), Lexile BR40L","description":"This book uses vibrant photographs to help students identify some common types of flowers. Simple sentences and high-frequency words support early-emergent readers. Students will have the opportunity to locate details that support the main idea as well as to ask and answer questions as they read this visually appealing book about flowers.","count":11,"from":1,"meta":["I","daisies, flowers, lilies, love, mums, poppies, roses, sunflowers, violets","Ask and answer questions to understand text","Main Idea and Details : Identify main idea and details","Initial Consonants : Discriminate initial consonant \/L\/ sound","Consonants : Identify initial consonant <i>Ll<\/i>","Pronouns : Recognize and use the pronoun <i>I<\/i>","Alphabetical Order : Understand and arrange words in alphabetical order","Promote higher-order thinking for small groups <br>or whole class"],"pdf":"raz_la39_iloveflowers"}