{"id":"1988","level":"l","title":"Kenya","subtle":"Informational (nonfiction), 404 words, Level L (Grade 2), Lexile 610L            \n                        \n\t\tMultilevel Book also available in levels                     U and Y","description":"Kenya covers many interesting facts about this African country, from amazing wildlife to the more than thirty tribes that live there. Students will enjoy learning about this beautiful country. Vibrant pictures and maps supplement the reading.","count":17,"from":1,"meta":[],"pdfs":["pdfsite\/nonbooks\/countries_around_the_world_country_maps\/caw_map_of_kenya.pdf","pdfsite\/comp_quiz\/l\/raz_cqll30_kenya.pdf"],"mis":{"clr":"pdfs\/levels\/l\/raz_ll30_kenya_clr_ds.pdf"}}