{"id":"2124","level":"m","title":"Wiggly Worms","subtle":"Informational (nonfiction), 475 words, Level M (Grade 2), Lexile 540L            \n                        \n\t\tMultilevel Book also available in levels                     G and J\t\t                 \n\t\tMultilevel Book also available in levels                     G and J","description":"Most people don't think much about the small and slimy earthworm, but worms actually have a big role in our environment. Wiggly Worms teaches students about a worm's body and behaviors, how it helps plants and other animals, and its place in the food chain. Photographs support the text. The book also presents opportunities for learning about main idea and details and adjectives. Book and lesson are also available for Levels G and J.","count":17,"from":1,"meta":["bristles, castings, cocoon, fertilizer, mate, mucus, muscle, nutrients, soil","Ask and answer questions to understand text","Main Idea and Details : Discern main idea and details","Variant Vowels : Identify variant vowel <i>oo<\/i>","Adjectives : Identify and use adjectives","Compound Words : Define and use compound words","Promote higher-order thinking for small groups <br>or whole class"],"pdf":"raz_lm27_wigglyworms"}