{"id":"2318","level":"z1","title":"Empire State Building","subtle":"Informational (nonfiction), 1,965 words, Level Z1 (Grade 5+), Lexile 1120L            \n                        \n\t\tMultilevel Book also available in levels                     M and V","description":"The Empire State Building has been a hallmark of the New York City skyline since its completion in 1931. This book will fascinate students with information about the building's construction and history.","count":22,"from":0,"meta":[],"pdf":"raz_lz12_empirestatebuilding"}