{"id":"2325","level":"b","title":"Bridges","subtle":"Informational (nonfiction), 40 words, Level B (Grade K), Lexile BR70L","description":"Bridges focuses on the diversity of bridges in our world, exploring their size, shape, and function. A simple repetitive sentence structure will support early emergent readers, as will the vivid photographs that accompany the text. Students can also use the book to learn about making inferences and using adjectives.","count":12,"from":0,"meta":["are, from, some","bridges, made, metal, rope, stone, wood","Ask and answer questions","Make Inferences\/Draw Conclusions : Make inferences \/ draw conclusions","Initial Consonants : Discriminate initial consonant <i>br<\/i>-blend","Consonant Blends : Identify initial consonant <i>br<\/i>-blend","Adjectives : Identify adjectives","Antonyms : Recognize and use antonyms","Promote higher-order thinking for small groups <br>or whole class"],"pdf":"raz_lb58_bridges"}