{"bookId":"2618","level":"f","title":"Battery Power!","subtle":"Informational (nonfiction), 126 words, Level F (Grade 1), Lexile 390L","description":"Batteries can power so many things! In Battery Power! students will learn how batteries work and what they can power. Detailed photographs, high-frequency words, and simple sentences support beginning readers. Students will also have the opportunity to connect to prior knowledge as well as to identify the main idea and details in order to better understand the text.","pageCount":14,"highFrequencyWords":"can, many, they","reviewWords":"batteries, charged, chemicals, electricity, energy, power","comprehension":"Main Idea and Details                : Identify the main idea and details in a text","awareness":"Segment Phonemes                : Segment phonemes","phonics":"Consonants                : Identify initial consonant <i>Bb<\/i>","grammar":"Verbs                : Recognize and use verbs","wordWork":"High-Frequency Words                : Identify and use the high-frequency word<i> they<\/i>","pdfName":"raz_lf50_batterypower"}