{"id":"2810","level":"x","title":"A Little Princess (Part 5)","subtle":"Classic (fiction), 3,377 words, Level X (Grade 5), Lexile 1030L","description":"Sara is a natural storyteller, with an ability to invent tales of all kinds. One day, while Sara sits spinning a yarn in her room for the other girls, she notices a scullery maid, Becky, slowing her work in order to listen. Sara feels instant compassion for the girl. A few days later, Sara finds Becky asleep in her armchair, in front of the warm fire, exhausted from her labors. When Becky awakes, Sara speaks kindly to her and feeds her cake. She tells Becky that if she comes to her room again, Sara will tell Becky another story.","count":26,"from":0,"meta":["Use the reading strategy of summarizing to understand the story","Analyze Point Of View : Identify the character point of view and determine how it affects the story","Pronouns : Identify and use pronoun agreement","Dialect : Identify and understand dialects"],"pdfs":["pdfsite\/comp_quiz\/x\/raz_cqlx28_littleprincesspart5.pdf"],"mis":{"clr":"pdfsite\/levels\/x_ds\/raz_lx28_littleprincesspart5_clr_ds.pdf"}}