{"bookId":"282","level":"m","title":"The Umbrella Trick","subtle":"Fantasy (fiction), 685 words, Level M (Grade 2), Lexile 480L, Fiction Series","description":"Snubby Nose and Grandpa Grizzly play a trick on the other Hoppers. They give them little umbrellas that are really pens. The Hoppers get wet, and this makes them angry. Grandpa Grizzly buys all the bunnies little silk umbrellas so they don't get wet.","pageCount":17,"highFrequencyWords":"disappointed, handle, manners, poured, silk, whistled","reviewWords":"Use of vocabulary lessons requires a subscription to VocabularyA-Z.com.","comprehension":"Vowel Digraphs                : Fluently read long \/e\/ vowel digraphs","awareness":"Contractions                : Identify and use contractions","phonics":"Alphabetizing                : Arrange words in alphabetical order","grammar":"Promote higher-order thinking for small groups <br>or whole class","wordWork":"","pdfName":"raz_th04_umbrellatrick"}