{"bookId":"2905","level":"g","title":"Meet the Beetles","subtle":"Informational (nonfiction), 140 words, Level G (Grade 1), Lexile 490L","description":"Beetles are amazing insects. There are more kinds of beetles than any other living creature on the planet. Meet the Beetles provides students with a comprehensive look at these fascinating insects. The book can also be used to teach students how to identify the main idea and supporting details and the proper use of simple predicates.","pageCount":14,"highFrequencyWords":"can, eat, live","reviewWords":"beetles, deserts, insects, jungles, skeleton, waste","comprehension":"Main Idea and Details                : Determine the main idea and details of a text","awareness":"Short Vowel Sounds                : Discriminate short vowel \/i\/ sound","phonics":"Short Vowels                : Identify short vowel <i>i<\/i>","grammar":"Simple Predicates                : Recognize and use simple predicates","wordWork":"High-Frequency Words                : Identify and use the high-frequency words <i>can, eat, live<\/i>","pdfName":"raz_lg46_meetbeetles"}