{"bookId":"2938","level":"s","title":"Mortyangelo and the Mystery Art","subtle":"Fantasy (fiction), 1,166 words, Level S (Grade 3), Lexile 840L, Fiction Series","description":"In Mortyangelo and the Mystery Art, an unsigned piece of artwork hangs in the hallway of Morty's school, and no one will claim it. As students gather around to admire the masterpiece, Morty secretly worries about what his classmates will think of him if he claims his art and signs it. With a little help from his art teacher, Morty finally makes a decision about his mystery art. An engaging storyline and colorful illustrations will keep students engaged in this relatable topic. The book can also be used to teach students how to analyze characters as well as identify and use quotation marks.","pageCount":18,"highFrequencyWords":"apprenticed, chapel, chiseled, circulated, engraved, indignant, masterpiece, radiant, renowned","reviewWords":"Use of vocabulary lessons requires a subscription to VocabularyA-Z.com.","comprehension":"Quotation Marks                : Recognize and use quotation marks","awareness":"Compound Words                : Identify and use compound words","phonics":"Promote higher-order thinking for small groups <br>or whole class","grammar":"","wordWork":"","pdfName":"raz_ls37_mortyangeloandmysteryart"}