{"id":"2960","level":"c","title":"The Festival of Lights","subtle":"Informational (nonfiction), 61 words, Level C (Grade K), Lexile 140L","description":"The lighting of the Hanukkah candles is a specific process that takes place during the eight nights of Hanukkah. The Festival of Lights introduces readers to the celebration of Hanukkah by teaching them how many candles are lit on each night. The book's descriptive photographs and repetitive sentence pattern support early emergent readers. Students will also have the opportunity to determine the author's purpose for writing and to visualize to better understand what is read.","count":12,"from":0,"meta":["is, on, the","candle, festival, Hanukkah, lights, middle, night","Visualize to understand text","Author's Purpose : Determine author's purpose","Word Awareness : Identify words","Consonants : Identify final consonant <i>Tt<\/i>","Periods : Recognize and use periods","Concept Words : Recognize number words","Promote higher-order thinking for small groups <br>or whole class"],"pdf":"raz_lc61_festivaloflights"}