{"id":"3052","level":"u","title":"Beowulf","subtle":"Classic (fiction), 2,043 words, Level U (Grade 4), Lexile 660L            \n                        \n\t\tMultilevel Book also available in levels                     X and Z1","description":"Derived from the classic tale, Beowulf is the story of a mighty warrior and king. Through his super-human strength and noble qualities, Beowulf is able to slay monsters and dragons that no other man can defeat. Detailed illustrations support a rich and engaging text. The book can also be used to teach students how to analyze characters and to identify irregular past-tense verbs. The book and lesson are also available for levels X and Z1.","count":18,"from":0,"meta":["barrow, coronet, fame, fate, fiend, handiwork, hilt, mead, might, moors, perish, vowed","Summarize to understand text","Analyze Character : Analyze characters within a text","Irregular Verbs : Recognize and use irregular verbs","Suffixes : Identify and use suffix <i>-ly<\/i>","Promote higher-order thinking for small groups <br>or whole class"],"pdfs":["pdfsite\/3052\/raz_lu26_beowulf_wksh.pdf","pdfsite\/3052\/raz_lu26_beowulf_wksh_rc.pdf","pdfsite\/3052\/raz_lu26_beowulf_wksh_gm.pdf","pdfsite\/3052\/raz_lu26_beowulf_wksh_ww.pdf","pdfsite\/discussion\/u\/raz_dclu26_beowulf.pdf","pdfsite\/comp_quiz\/u\/raz_cqlu26_beowulf.pdf"],"mis":{"clr":"pdfsite\/levels\/u_ds\/raz_lu26_beowulf_clr_ds.pdf","lblp":"pdfsite\/3052\/raz_lu26_beowulf_lblp.pdf"}}