{"bookId":"3087","level":"k","title":"Jackie Robinson","subtle":"Biography (nonfiction), 402 words, Level K (Grade 2), Lexile 700L            \n                        \n\t\tMultilevel Book also available in levels                     N and Q\t\t                 \n\t\tMultilevel Book also available in levels                     N and Q","description":"Baseball is known as America's pastime, and many people enjoy playing and watching this sport. But, did you know there was a time when black athletes were not allowed to play on the same teams as white athletes? Jackie Robinson tells the story of the man who changed that. Detailed photographs and engaging text will keep students interested in this important part of American history. The book can also be used to teach students how to identify elements of a biography as well as to create a summary to better understand the text. The book and lesson are also available for levels N and Q.","pageCount":18,"highFrequencyWords":"athletes, condition, prejudice, professional, rights, segregated","reviewWords":"Use of vocabulary lessons requires a subscription to VocabularyA-Z.com.","comprehension":"Consonant Digraphs                : Identify consonant digraph <i>wh<\/i>","awareness":"Declarative Sentences                : Recognize and use declarative sentences","phonics":"Homographs                : Identify and use homographs correctly in sentences","grammar":"Promote higher-order thinking for small groups <br>or whole class","wordWork":"","pdfName":"raz_lk29_jackierobinson"}