{"bookId":"3116","level":"b","title":"Healthy Snacks","subtle":"Descriptive (nonfiction), 32 words, Level B (Grade K), Lexile BR40L","description":"What kinds of snacks are good for you? Healthy Snacks provides students a glimpse of a few healthy snacks from fruits and vegetables to nuts and more! Vibrant photographs and a repetitive text pattern will support early readers. This book can also be used to teach students how to classify information and how to identify and use nouns.","pageCount":12,"highFrequencyWords":"be, can","reviewWords":"celery, cereal, cheese, healthy, seeds, snacks","comprehension":"Classify Information                : Classify information in text","awareness":"Initial and Final Sounds                : Discriminate initial consonant \/s\/ sound","phonics":"Consonants                : Identify initial consonant <i>Ss<\/i>","grammar":"Nouns                : Recognize and use nouns","wordWork":"High-Frequency Words                : Identify and use the high-frequency words <i>be<\/i> and <i>can<\/i>","pdfName":"raz_lb72_healthysnacks"}