{"id":"3289","level":"v","title":"Tokyo Imperial Palace","subtle":"Informational (nonfiction), 1,270 words, Level V (Grade 4), Lexile 920L            \n                        \n\t\tMultilevel Book also available in levels                     M and Z1","description":"In the center of the city of Tokyo, Japan lies the Imperial Palace. The grounds were originally home to a shogun's castle. The palace was built on the castle grounds in 1888. It combined both Eastern architecture and European design. The site is of great historical, cultural and artistic significance to Japan. Students will learn about the palace's history and construction, and its famous public gardens.","count":18,"from":0,"meta":[],"pdfs":["pdfsite\/nonbooks\/world_landmarks_posters\/tokyo_imperial_palace.pdf","pdfsite\/comp_quiz\/v\/raz_cqlv29_tokyoimperialpalace.pdf"],"mis":{"clr":"pdfsite\/levels\/v_ds\/raz_lv29_tokyoimperialpalace_clr_ds.pdf"}}