{"id":"3332","level":"j","title":"All About Snakes","subtle":"Informational (nonfiction), 376 words, Level J (Grade 1), Lexile 570L","description":"What is the first word that comes to mind when you think of snakes? Is it <i>gross<\/i> or <i>beautiful<\/i>? Is it <i>dangerous<\/i> or <i>amazing<\/i>? <i>All About Snakes<\/i> gives students the chance to decide how they feel about snakes! This text contains fascinating information about snakes, including where they live, how they hunt, and other interesting facts. Up-close and colorful photographs will keep students engaged with this exciting topic. This book can also be used to teach how to summarize a text as well as identify the main idea and details.","count":18,"from":0,"meta":["live, some, they","fangs, hibernate, prey, reptiles, scales, venom","Identify main idea and details","Summarize : Summarize to understand text","Initial Blends : Discriminate initial consonant <i>sn<\/i> blend","Consonant Blends : Identify consonant <i>sn<\/i> blend","Verbs : Recognize and use verbs correctly in sentences","Synonyms and Antonyms : Identify and use synonyms and antonyms","Promote higher-order thinking for small groups <br>or whole class"],"pdfs":["pdfsite\/3332\/raz_lj43_allaboutsnakes_wksh.pdf","pdfsite\/3332\/raz_lj43_allaboutsnakes_wksh_rs.pdf","pdfsite\/3332\/raz_lj43_allaboutsnakes_wksh_gm.pdf","pdfsite\/3332\/raz_lj43_allaboutsnakes_wksh_ww.pdf","pdfsite\/discussion\/j\/raz_dclj43_allaboutsnakes.pdf","pdfsite\/comp_quiz\/j\/raz_cqlj43_allaboutsnakes.pdf"],"mis":{"clr":"pdfsite\/levels\/j_ds\/raz_lj43_allaboutsnakes_clr_ds.pdf","lblp":"pdfsite\/3332\/raz_lj43_allaboutsnakes_lblp.pdf"}}