{"id":"3475","level":"e","title":"Goodbye Snow","subtle":"Informational (nonfiction), 89 words, Level E (Grade 1), Lexile 230L","description":"Snow is a beautiful sight, but sometimes it can get in the way. Explore the many ways snow can be removed in <i>Goodbye Snow.<\/i> This book teaches students about the different tools used to remove snow, with engaging photographs and simple sentences. Students will also have the opportunity to make inferences and draw conclusions as well as to ask and answer questions to better understand the text.","count":14,"from":0,"meta":["away, be, can","removed, shovel, snow dumps, snow melter, snowblower, snowplow","Ask and answer questions to understand text","Make Inferences\/Draw Conclusions : Make inferences and draw conclusions","Segment Syllables : Segment syllables","Consonant Blends : Identify initial consonant <i>sn-<\/i>blends","Declarative Sentences : Recognize and use declarative sentences","Compound Words : Identify and use compound words","Promote higher-order thinking for small groups <br>or whole class"],"pdf":"raz_le70_goodbyesnow"}