{"bookId":"3490","level":"m","title":"The Legend of the Giant's Causeway","subtle":"Legend (fiction), 531 words, Level M (Grade 2), Lexile 530L            \n                        \n\t\tMultilevel Book also available in levels                     J and P","description":"The Giant's Causeway, one of the most popular sites in Northern Ireland, is a natural staircase stretching into the sea. This story is the delightful legend of how this causeway came to be. It details the crafty plan that puts a stop to Cucullin, the strongest giant--and biggest bully--around. <i>The Legend of the Giant's Causeway<\/i> is an entertaining tale supported by colorful illustrations. The book can also be used to teach students how to make inferences and draw conclusions and to identify and use quotation marks. The book and lesson are also available for levels J and P.","pageCount":18,"highFrequencyWords":"cradle, giant, Ireland, iron, Scotland, thunderbolt","reviewWords":"Use of vocabulary lessons requires a subscription to VocabularyA-Z.com.","comprehension":"Consonant Digraphs                : Identify consonant digraph <i>wh<\/i>","awareness":"Quotation Marks                : Recognize and use quotation marks","phonics":"Suffixes                : Identify and use the suffix <i>-ing<\/i>","grammar":"Promote higher-order thinking for small groups <br>or whole class","wordWork":"","pdfName":"raz_lm27_legendofgiantscauseway"}