{"id":"3534","level":"a","title":"This Looks","subtle":"Concept (fiction), 32 words, Level A (Grade K), Lexile BR60L","description":"In <i>This Looks<\/i>, readers follow a curious owl as it comes upon things that can be described in many different ways. A variety of environments provide students with rich descriptions. Predictable text combined with charming illustrations make this book a perfect fit for emerging readers. The text allows students to draw on their prior knowledge to make connections as well as identify cause-and-effect relationships.","count":12,"from":0,"meta":["look, so, this","dirty, funny, pretty, shiny, ugly, wild","Connect to prior knowledge to better understand text","Cause and Effect : Identify cause-and-effect relationships","Initial Consonants : Discriminate initial consonant <i>\/b\/<\/i> sound","Consonants : Identify initial consonant <i>Ss<\/i>","Periods : Recognize and use periods","High-Frequency Words : Identify and use high-frequency word <i>this<\/i>","Promote higher-order thinking for small groups <br>or whole class"],"pdfs":["pdfsite\/3534\/raz_la64_thislooks_wksh.pdf","pdfsite\/3534\/raz_la64_thislooks_wksh_rc.pdf","pdfsite\/3534\/raz_la64_thislooks_wksh_ph.pdf","pdfsite\/3534\/raz_la64_thislooks_wksh_gm.pdf","pdfsite\/discussion\/a\/raz_dcla64_thislooks.pdf","pdfsite\/comp_quiz\/a\/raz_cqla64_thislooks.pdf"],"mis":{"clr":"pdfsite\/levels\/a_ds\/raz_la64_thislooks_clr_ds.pdf","lblp":"pdfsite\/3534\/raz_la64_thislooks_lblp.pdf"}}