{"id":"3612","level":"z2","title":"Napoleon Bonaparte","subtle":"Informational (nonfiction), 2,136 words, Level Z2 (Grade 5+), Lexile 1050L            \n                        \n\t\tMultilevel Book also available in levels                     T and Z","description":"In the turmoil following the French Revolution, a young military commander, Napoleon Bonaparte, rises to power. After proving himself on the battlefield, Napoleon becomes the leader (and eventually emperor) of France. Under his brilliant leadership, French armies sweep across Europe, expanding the empire. He seems unstoppable until a disastrous invasion of Russia in 1812 sows the seeds for his downfall.","count":22,"from":0,"meta":[],"pdf":"raz_lz26_napolonbonaparte"}