{"id":"3723","level":"w","title":"Taiga","subtle":"Informational (nonfiction), 1,307 words, Level W (Grade 4), Lexile 1020L","description":"Earth is covered with several distinct biomes. <em>Taiga<\/em> introduces students to the planet's largest land biome through vivid photographs and detailed information. Students will learn about the different features of this biome including its climate and wildlife, as well as the people who call the taiga home. This book can also be used to teach students how to identify the main idea and supporting details.","count":18,"from":0,"meta":["adaptations, bogs, conifers, hardiest, industrial, insulation, migrate, nutrient, organic, photosynthesis, precipitation, taiga","Summarize to understand text","Main Idea and Details : Identify main idea and details","Adjectives : Recognize and use adjectives","Compound Words : Identify and use compound words","Promote higher-order thinking for small groups <br>or whole class"],"pdfs":["pdfsite\/3723\/raz_lw29_taiga_wksh.pdf","pdfsite\/3723\/raz_lw29_taiga_wksh_rc.pdf","pdfsite\/3723\/raz_lw29_taiga_wksh_gm.pdf","pdfsite\/3723\/raz_lw29_taiga_wksh_ww.pdf","pdfsite\/discussion\/w\/raz_dclw29_taiga.pdf","pdfsite\/comp_quiz\/w\/raz_cqlw29_taiga.pdf"],"mis":{"clr":"pdfsite\/levels\/w_ds\/raz_lw29_taiga_clr_ds.pdf","lblp":"pdfsite\/3723\/raz_lw29_taiga_lblp.pdf"}}