{"id":"3833","level":"u","title":"How Bees Make Honey","subtle":"Informational (nonfiction), 1,114 words, Level U (Grade 4), Lexile 1020L","description":"Did you know that a hive of bees must fly nearly fifty-five thousand miles and visit two million flowers to produce a pound of honey? These incredible creatures work together in an intricate and fascinating system to create a food source for themselves as well as other species. <em>How Bees Make Honey<\/em> details the sequence of events necessary to fill a single honeycomb cell and explains the importance of protecting and preserving bees. The book can also be used to teach students how to effectively sequence events and the proper use of prepositional phrases.","count":18,"from":0,"meta":["abdomens, capped, cooperation, critical, digesting, evaporates, fertilization, foragers, glands, nurture, pollen, substance","Summarize to understand text","Sequence Events : Determine a sequence of events","Prepositional Phrases : Recognize and use prepositional phrases","Compound Words : Identify and use closed compound words","Promote higher-order thinking for small groups <br>or whole class"],"pdfs":["pdfsite\/3833\/raz_lu26_howbeesmakehoney_wksh.pdf","pdfsite\/3833\/raz_lu26_howbeesmakehoney_wksh_rc.pdf","pdfsite\/3833\/raz_lu26_howbeesmakehoney_wksh_gm.pdf","pdfsite\/3833\/raz_lu26_howbeesmakehoney_wksh_ww.pdf","pdfsite\/discussion\/u\/raz_dclu26_howbeesmakehoney.pdf","pdfsite\/comp_quiz\/u\/raz_cqlu26_howbeesmakehoney.pdf"],"mis":{"clr":"pdfsite\/level\/u_ds\/raz_lu26_howbeesmakehoney_clr_ds.pdf","lblp":"pdfsite\/3833\/raz_lu26_howbeesmakehoney_lblp.pdf"}}