{"id":"3884","level":"b","title":"Fun with Paper","subtle":"Concept (nonfiction), 32 words, Level B (Grade K), Lexile BR30L","description":"So many projects use paper. In <em>Fun with Paper,<\/em> students will read about different things they can do with paper. The detailed, colorful photographs; high-frequency words; and repetitive sentence patterns will support early readers. The book can be also used to teach students how to identify the main idea and details, as well as how to locate and use verbs.","count":12,"from":0,"meta":["be, can, you","change, fold, glue, paper, tape, tear","Connect to prior knowledge to understand text","Main Idea and Details : Identify main idea and details","Word Awareness : Build word awareness","Consonants : Identify initial consonant <i>Pp<\/i>","Verbs : Identify and use verbs","High-Frequency Words : Identify and use high-frequency words <i>be, can, you<\/i>","Promote higher-order thinking for small groups <br>or whole class"],"pdf":"raz_lb82_funwithpaper"}