{"id":"3898","level":"i","title":"Dolphins","subtle":"Informational (nonfiction), 254 words, Level I (Grade 1), Lexile 530L","description":"Did you know that dolphins can talk to each other and play catch? In <em>Dolphins,<\/em> students will learn many interesting facts about these fascinating animals. Dolphins come in different sizes and can live in different places, but they also share some amazing traits as well. The book can also be used to teach students how to determine the main idea and details as well as the proper use of capital letters.","count":18,"from":0,"meta":["live, they, use","female, grab, mammals, pods, protect, steer","Visualize to understand text","Main Idea and Details : Determine main idea and details","Initial and Final Blends : Discriminate initial consonant <i>gr<\/i>-blend","Consonant Digraphs : Identify consonant digraph <i>ph<\/i>","Capitalization : Use capital letters correctly","Synonyms : Identify and use synonyms","Promote higher-order thinking for small groups <br>or whole class"],"pdfs":["pdfsite\/3898\/raz_li48_dolphins_wksh.pdf","pdfsite\/3898\/raz_li48_dolphins_wksh_rc.pdf","pdfsite\/3898\/raz_li48_dolphins_wksh_gm.pdf","pdfsite\/3898\/raz_li48_dolphins_wksh_ww.pdf","pdfsite\/discussion\/i\/raz_dcli48_dolphins.pdf","pdfsite\/comp_quiz\/i\/raz_cqli48_dolphins.pdf"],"mis":{"clr":"pdfsite\/levels\/i_ds\/raz_li48_dolphins_clr_ds.pdf","lblp":"pdfsite\/3898\/raz_li48_dolphins_lblp.pdf"}}