{"id":"3930","level":"s","title":"Polar Bear's Promise","subtle":"Fairy Tale (fiction), 1,071 words, Level S (Grade 3), Lexile 760L","description":"<em>Polar Bear's Promise<\/em> is a fun and fresh take on the classic fairy tale Little Red Riding Hood. Instead of Little Red Riding Hood meeting a wolf in the woods on the way to her grandmother's house, Amka meets a polar bear in the Arctic. The polar bear is hungry and eats Amka and her grandmother, but things don't turn out quite the way he expects. Colorful illustrations and an engaging storyline will keep students interested in this modern fairy tale. The book can also be used to teach students how to analyze characters in a text as well as to make, revise, and confirm predictions.","count":18,"from":0,"meta":["appetizing, crimson, devoured, frigid, peculiar, recede, savor, scrumptious, suspicious","Make, revise, and confirm predictions","Analyze Character : Analyze characters in a text","Contractions : Recognize and use contractions","Compound Words : Identify and use open compound words","Promote higher-order thinking for small groups <br>or whole class"],"pdfs":["pdfsite\/3930\/raz_ls35_polarbearspromise_wksh.pdf","pdfsite\/3930\/raz_ls35_polarbearspromise_wksh_rc.pdf","pdfsite\/3930\/raz_ls35_polarbearspromise_wksh_gm.pdf","pdfsite\/3930\/raz_ls35_polarbearspromise_wksh_ww.pdf","pdfsite\/discussion\/s\/raz_dcls35_polarbearspromise.pdf","pdfsite\/comp_quiz\/s\/raz_cqls35_polarbearspromise.pdf"],"mis":{"clr":"pdfsite\/levels\/s_ds\/raz_ls35_polarbearspromise_clr_ds.pdf","lblp":"pdfsite\/3930\/raz_ls35_polarbearspromise_lblp.pdf"}}