{"bookId":"629","level":"y","title":"Leaving Home","subtle":"Realistic (fiction), 2,852 words, Level Y (Grade 5), Lexile 920L","description":"Leaving Home is a fictional narrative about a boy who has moved from Jamaica to the United States. The story details how it would feel to leave everything familiar behind to begin a new life. Students will personally relate to this story if they have ever moved to a new country, state, or even neighborhood.","pageCount":23,"highFrequencyWords":"adorned, detachment, gloss, incessantly, laden, mayhem, patois, quirks, reprieve, savory, stupefied, vigil","reviewWords":"Use of vocabulary lessons requires a subscription to VocabularyA-Z.com.","comprehension":"Verbs and Adverbs                : Identify and use action verbs and adverbs that show feelings","awareness":"Content Vocabulary                : Understand content vocabulary","phonics":"Promote higher-order thinking for small groups <br>or whole class","grammar":"","wordWork":"","pdfName":"raz_ly03_leavinghome"}