{"bookId":"64","level":"e","title":"A Week With Grandpa","subtle":"Realistic (fiction), 102 words, Level E (Grade 1), Lexile 210L","description":"A Week with Grandpa is the story of a little boy who spends seven fun-filled days with his grandfather. The days of the week are presented in sequential order, with the boy and his grandfather engaging in a different activity each day.","pageCount":11,"highFrequencyWords":"saw, went","reviewWords":"Friday, Grandpa, Monday, Saturday, Sunday, Thursday, Tuesday, Wednesday","comprehension":"Sequence Events                : Sequence the events of a story","awareness":"Segment Onset and Rime                : Segment onset and rime","phonics":"Consonant Blends                : Identify initial consonant <em>r-<\/em>blends","grammar":"Proper Nouns                : Identify proper nouns","wordWork":"Days of the Week                : Read the days of the week","pdfName":"raz_le34_weekwithgrandpa"}