{"id":"65","level":"e","title":"Doctor Jen","subtle":"Realistic (fiction), 129 words, Level E (Grade 1), Lexile 240L","description":"Doctor Jen tells the story of family members who are ill and the doctor they visit to feel better. The one family member who cannot visit Doctor Jen is revealed on the last page of the book. The picture-to-text correspondence and familiar topics support early readers' efforts.","count":11,"from":1,"meta":["has, is, my","ache, cough, doctor, ill, knees, stiff","Use the strategy of retelling to understand the text","Problem and Solution : Identify the story elements of problem and solution","Blend Phonemes : Blend phonemes","Consonant Digraphs : Read words with consonant digraph <em>-ck<\/em>","Exclamatory Sentences : Capitalize and punctuate exclamatory sentences","Alphabetizing : Place words in alphabetical order","Promote higher-order thinking for small groups <br>or whole class"],"pdf":"raz_le04_drjen"}