{"bookId":"672","level":"k","title":"Gorillas","subtle":"Informational (nonfiction), 389 words, Level K (Grade 2), Lexile 560","description":"Gorillas are the largest primates in the world. They play tag with family members, make crying sounds when they're upset, and can even learn sign language to communicate with humans. <em>Gorillas<\/em> is an informative text that highlights how gorillas survive in the forests of Africa. Up-close photographs invite students to enter the gorillas' world. The book can also be used to teach students how to identify main idea and details as well as to summarize to better understand the text.","pageCount":18,"highFrequencyWords":"communicate, endangered, family, groom, lowlands, primates","reviewWords":"Use of vocabulary lessons requires a subscription to VocabularyA-Z.com.","comprehension":"Consonants                : Identify initial and final consonant <i>st<\/i>-blends","awareness":"Plural Nouns                : Recognize and use plural nouns","phonics":"Multiple Meaning Words                : Identify and use multiple-meaning words","grammar":"Promote higher-order thinking for small groups <br>or whole class","wordWork":"","pdfName":"raz_lk27_gorillas"}