{"id":"879","level":"a","title":"Up and Down","subtle":"Realistic (fiction), 24 words, Level A (Grade K), Lexile BR40L","description":"What goes up must come down. The book Up and Down illustrates this concept to students using familiar objects. The pictures, high-frequency words, and repetitive text support beginning readers as they read.","count":11,"from":1,"meta":["go, goes","dog, down, eyes, frog, hands, up","Connect to prior knowledge to understand text","Main Idea and Details : Identify main idea and details","Rhyme : Identify rhyming words","Consonants : Identify words with the initial consonant <em>Dd<\/em>","Periods : Recognize and understand the use of a period at the end of a sentence","High-Frequency Words : Recognize, write, and understand the use of high-frequency words <em>go<\/em> and <em>goes<\/em>","Promote higher-order thinking for small groups <br>or whole class"],"pdf":"raz_la37_upanddown"}