{"bookId":"908","level":"y","title":"The Legacy of da Vinci","subtle":"Biography (nonfiction), 2,195 words, Level Y (Grade 5), Lexile 1080L","description":"The Legacy of da Vinci is an informational book about the life of Leonardo da Vinci. Although he might be best known for artistic works such as The Mona Lisa and The Last Supper, da Vinci was also an avid inventor. His lifelong curiosity and observation of the world around him led him to develop ideas for such objects as clocks, cameras, helicopters, hydraulics, and hang gliders. These ideas, which resulted from his pursuit of knowledge, continue to fascinate people today. Photographs support the text.","pageCount":25,"highFrequencyWords":"anatomical, apprentice, camera obscura, commissions, guild, hydraulic, Industrial Revolution, innovative, novelty, prototypes, Renaissance, replica","reviewWords":"Use of vocabulary lessons requires a subscription to VocabularyA-Z.com.","comprehension":"Prepositions                : Identify and use prepositional phrases within sentences","awareness":"Suffixes                : Understand how the suffixes <em>-ful<\/em> and <em>-less<\/em> change the meaning of words","phonics":"Promote higher-order thinking for small groups <br>or whole class","grammar":"","wordWork":"","pdfName":"raz_ly17_legacyofdavinci"}